{
	"dialogue": [
		{
			"expression": "angry",
			"text": "MF WHY DID YOU CRASH INTO ME?!!",
			"boxState": "angry",
			"portrait": "dialogueaaron",
			"speed": 0.01,
			"sound": "aar"
		},
		{
			"expression": "talk",
			"text": "Worth it.",
			"boxState": "normal",
			"portrait": "anthony",
			"speed": 0.06,
			"sound": "anth"
		},
		{
			"expression": "angry",
			"text": "Nah you gonna pay now...",
			"boxState": "normal",
			"portrait": "dialogueaaron",
			"speed": 0.08,
			"sound": "aar"
		},
		{
			"expression": "talk",
			"text": "Oh really? Ooo I'm so scar-",
			"boxState": "normal",
			"portrait": "anthony",
			"speed": 0.05,
			"sound": "anth"
		},
		{
			"expression": "talk",
			"text": "Yeet.",
			"boxState": "normal",
			"portrait": "normalhalo",
			"speed": 0.00500000000000001,
			"sound": "halonoise"
		},
		{
			"expression": "talk",
			"text": "OW!! WAS THAT A MICROPHONE?!!",
			"boxState": "angry",
			"portrait": "anthony",
			"speed": 0.01,
			"sound": "anth"
		},
		{
			"expression": "bored",
			"text": "Yeah.",
			"boxState": "normal",
			"portrait": "dialogueaaron",
			"speed": 0.08,
			"sound": "aar"
		},
		{
			"expression": "talk",
			"text": "Alright, very well then...",
			"boxState": "normal",
			"portrait": "anthony",
			"speed": 0.05,
			"sound": "anth"
		},
		{
			"expression": "talk",
			"text": "We shall fight.",
			"boxState": "normal",
			"portrait": "anthony",
			"speed": 0.05,
			"sound": "anth"
		},
		{
			"expression": "happy",
			"text": "Alright bet-",
			"boxState": "normal",
			"portrait": "dialogueaaron",
			"speed": 0.03,
			"sound": "aar"
		},
		{
			"expression": "talk",
			"text": "Via singing.",
			"boxState": "normal",
			"portrait": "anthony",
			"speed": 0.05,
			"sound": "anth"
		},
		{
			"expression": "angry",
			"text": "BRUH.",
			"boxState": "angry",
			"portrait": "dialogueaaron",
			"speed": 0.01,
			"sound": "aar"
		}
	]
}